[
{
"ID":"",
"SkinName":"Mặc Định",
"Preview":"https://lienquan.garena.vn/files/skin/70ea305ed24716682532486c9625a8315cfe1cf692268.jpg",
"Sound":"",
"Ages":"",
"Prefab":"",
"Databin":"",
"Extra":"/154/154.zip"
},
{
"ID":"",
"SkinName":"Thỏ May Mắn",
"Preview":"https://lienquan.garena.vn/files/skin/54ea14e04a555d4e2fa57e48843b2b865db5892145f2b.jpg",
"Sound":"",
"Ages":"",
"Prefab":"",
"Databin":"",
"Extra":"/154/15402.zip"
},
{
"ID":"",
"SkinName":"Chiến Binh Nguyệt Tộc",
"Preview":"https://lienquan.garena.vn/files/skin/42442c73fdbed30616da2d7bff0a8b435ed48aa72f41a.jpg",
"Sound":"",
"Ages":"",
"Prefab":"",
"Databin":"",
"Extra":"/154/15403.zip"
},
{
"ID":"",
"SkinName":"Dạ Nguyệt Thánh Nữ",
"Preview":"https://lienquan.garena.vn/files/skin/182eaa432f1444b31b7f573acb9546a25fbb734ee15d4.jpg",
"Sound":"",
"Ages":"",
"Prefab":"",
"Databin":"",
"Extra":"/154/15406.zip"
},
{
"ID":"",
"SkinName":"Giảng Viên Tình Ái",
"Preview":"https://lienquan.garena.vn/files/skin/18f031e397da0bf519acd964bc4754ca61178b9a4091f.png",
"Sound":"",
"Ages":"",
"Prefab":"",
"Databin":"",
"Extra":"/154/15407.zip"
},
{
"ID":"",
"SkinName":"WAVE",
"Preview":"https://github.com/JaneAoV/DN_Turbo_Project/raw/main/MODSKINNEW/ModFullSkin/SkinImage/154/1549.jpg",
"Sound":"",
"Ages":"",
"Prefab":"",
"Databin":"",
"Extra":"/154/15409.zip"
}
]
